{
	"info": {
		"_postman_id": "5ce7fcc7-4786-48b5-a01f-b1ef7c292cd3",
		"name": "Order Management API",
		"schema": "https://schema.getpostman.com/json/collection/v2.1.0/collection.json",
		"_exporter_id": "36261573"
	},
	"item": [
		{
			"name": "Auth",
			"item": [
				{
					"name": "register",
					"request": {
						"method": "POST",
						"header": [],
						"body": {
							"mode": "raw",
							"raw": "{\r\n  \"name\": \"Test User\",\r\n  \"email\": \"Lin9999@example.com\",\r\n  \"password\": \"12345678\"\r\n  \r\n}",
							"options": {
								"raw": {
									"language": "json"
								}
							}
						},
						"url": {
							"raw": "http://localhost:3000/api/auth/register",
							"protocol": "http",
							"host": [
								"localhost"
							],
							"port": "3000",
							"path": [
								"api",
								"auth",
								"register"
							]
						}
					},
					"response": []
				},
				{
					"name": "login",
					"request": {
						"method": "POST",
						"header": [],
						"body": {
							"mode": "raw",
							"raw": "{\r\n   \"email\": \"Linh0036@example.com\",\r\n  \"password\": \"123456\"\r\n}",
							"options": {
								"raw": {
									"language": "json"
								}
							}
						},
						"url": {
							"raw": "http://localhost:3000/api/login",
							"protocol": "http",
							"host": [
								"localhost"
							],
							"port": "3000",
							"path": [
								"api",
								"login"
							]
						}
					},
					"response": []
				}
			]
		},
		{
			"name": "Products",
			"item": [
				{
					"name": "Tìm và lọc",
					"protocolProfileBehavior": {
						"disableBodyPruning": true
					},
					"request": {
						"method": "GET",
						"header": [],
						"body": {
							"mode": "raw",
							"raw": "    {\r\n            \"name\": \"nam\",\r\n            \"price\": \"999.99\",\r\n            \"stock\": 10,\r\n            \"description\": \"High performance laptop\",\r\n            \"category\": \"linh\"\r\n   }",
							"options": {
								"raw": {
									"language": "json"
								}
							}
						},
						"url": {
							"raw": "http://localhost:3000/api/products?category=nam",
							"protocol": "http",
							"host": [
								"localhost"
							],
							"port": "3000",
							"path": [
								"api",
								"products"
							],
							"query": [
								{
									"key": "category",
									"value": "nam"
								}
							]
						}
					},
					"response": []
				},
				{
					"name": "Add Product",
					"request": {
						"auth": {
							"type": "bearer",
							"bearer": [
								{
									"key": "token",
									"value": "eyJhbGciOiJIUzI1NiIsInR5cCI6IkpXVCJ9.eyJpZCI6MTEsInJvbGUiOiJhZG1pbiIsImlhdCI6MTc0NTM5NzQ4MSwiZXhwIjoxNzQ1NDAxMDgxfQ.PKfpGhKUPAuDirVWAh1AYR-VmsFapBnTT6TWvFfUn0w",
									"type": "string"
								}
							]
						},
						"method": "POST",
						"header": [
							{
								"key": "token",
								"value": "eyJhbGciOiJIUzI1NiIsInR5cCI6IkpXVCJ9.eyJpZCI6MTEsInJvbGUiOiJhZG1pbiIsImlhdCI6MTc0NTM5NzQ4MSwiZXhwIjoxNzQ1NDAxMDgxfQ.PKfpGhKUPAuDirVWAh1AYR-VmsFapBnTT6TWvFfUn0w",
								"type": "text",
								"disabled": true
							}
						],
						"body": {
							"mode": "raw",
							"raw": "  {\r\n    \"name\": \"Laptop\",\r\n    \"price\": 999.99,\r\n    \"stock\": 10,\r\n    \"category\": \"electronics\",\r\n    \"description\": \"High performance laptop\"\r\n  }",
							"options": {
								"raw": {
									"language": "json"
								}
							}
						},
						"url": {
							"raw": "http://localhost:3000/api/products/admin/products",
							"protocol": "http",
							"host": [
								"localhost"
							],
							"port": "3000",
							"path": [
								"api",
								"products",
								"admin",
								"products"
							]
						}
					},
					"response": []
				},
				{
					"name": "Update Product",
					"request": {
						"auth": {
							"type": "bearer",
							"bearer": [
								{
									"key": "token",
									"value": "eyJhbGciOiJIUzI1NiIsInR5cCI6IkpXVCJ9.eyJpZCI6MTEsInJvbGUiOiJhZG1pbiIsImlhdCI6MTc0NTM5NzQ4MSwiZXhwIjoxNzQ1NDAxMDgxfQ.PKfpGhKUPAuDirVWAh1AYR-VmsFapBnTT6TWvFfUn0w",
									"type": "string"
								}
							]
						},
						"method": "PUT",
						"header": [],
						"body": {
							"mode": "raw",
							"raw": "{\r\n    \"name\": \"Lapt\",\r\n    \"price\": 999,\r\n    \"stock\": 15,\r\n    \"category\": \"electronics\",\r\n    \"description\": \"High performance laptop\"\r\n  }",
							"options": {
								"raw": {
									"language": "json"
								}
							}
						},
						"url": {
							"raw": "http://localhost:3000/api/products/admin/products/1",
							"protocol": "http",
							"host": [
								"localhost"
							],
							"port": "3000",
							"path": [
								"api",
								"products",
								"admin",
								"products",
								"1"
							]
						}
					},
					"response": []
				},
				{
					"name": "Delete Product",
					"request": {
						"auth": {
							"type": "bearer",
							"bearer": [
								{
									"key": "token",
									"value": "eyJhbGciOiJIUzI1NiIsInR5cCI6IkpXVCJ9.eyJpZCI6MTEsInJvbGUiOiJhZG1pbiIsImlhdCI6MTc0NTM5NzQ4MSwiZXhwIjoxNzQ1NDAxMDgxfQ.PKfpGhKUPAuDirVWAh1AYR-VmsFapBnTT6TWvFfUn0w",
									"type": "string"
								}
							]
						},
						"method": "DELETE",
						"header": [],
						"body": {
							"mode": "raw",
							"raw": "",
							"options": {
								"raw": {
									"language": "json"
								}
							}
						},
						"url": {
							"raw": "http://localhost:3000/api/products/admin/products/1",
							"protocol": "http",
							"host": [
								"localhost"
							],
							"port": "3000",
							"path": [
								"api",
								"products",
								"admin",
								"products",
								"1"
							]
						}
					},
					"response": []
				}
			]
		},
		{
			"name": "Orders",
			"item": [
				{
					"name": "User routes",
					"protocolProfileBehavior": {
						"disableBodyPruning": true
					},
					"request": {
						"auth": {
							"type": "bearer",
							"bearer": [
								{
									"key": "token",
									"value": "eyJhbGciOiJIUzI1NiIsInR5cCI6IkpXVCJ9.eyJpZCI6Mywicm9sZSI6ImxvY2tlZCIsImlhdCI6MTc0NTQwMDcwOCwiZXhwIjoxNzQ1NDA0MzA4fQ.4ZETxTBY5gzWXQs4-CIU0x0hqVzIk42H0m7OgGF9xKI",
									"type": "string"
								}
							]
						},
						"method": "GET",
						"header": [],
						"body": {
							"mode": "raw",
							"raw": "",
							"options": {
								"raw": {
									"language": "json"
								}
							}
						},
						"url": {
							"raw": "http://localhost:3000/api/orders",
							"protocol": "http",
							"host": [
								"localhost"
							],
							"port": "3000",
							"path": [
								"api",
								"orders"
							]
						}
					},
					"response": []
				},
				{
					"name": "User routes",
					"request": {
						"auth": {
							"type": "bearer",
							"bearer": [
								{
									"key": "token",
									"value": "eyJhbGciOiJIUzI1NiIsInR5cCI6IkpXVCJ9.eyJpZCI6Mywicm9sZSI6InVzZXIiLCJpYXQiOjE3NDU0MDIyOTMsImV4cCI6MTc0NTQwNTg5M30.3CV3wyHYuGyukca1nBAvGBQIbxGXroipVZ0NEE81dZ4",
									"type": "string"
								}
							]
						},
						"method": "POST",
						"header": [],
						"body": {
							"mode": "raw",
							"raw": "  {\r\n    \"items\": [\r\n      {\r\n        \"productId\": 2,\r\n        \"quantity\": 2\r\n      },\r\n      {\r\n        \"productId\": 4,\r\n        \"quantity\": 6\r\n      }\r\n    ]\r\n  }",
							"options": {
								"raw": {
									"language": "json"
								}
							}
						},
						"url": {
							"raw": "http://localhost:3000/api/orders",
							"protocol": "http",
							"host": [
								"localhost"
							],
							"port": "3000",
							"path": [
								"api",
								"orders"
							]
						}
					},
					"response": []
				},
				{
					"name": "Admin routes",
					"request": {
						"method": "GET",
						"header": [],
						"url": {
							"raw": "http://localhost:3000/api/orders/admin/orders/:id/status",
							"protocol": "http",
							"host": [
								"localhost"
							],
							"port": "3000",
							"path": [
								"api",
								"orders",
								"admin",
								"orders",
								":id",
								"status"
							],
							"variable": [
								{
									"key": "id",
									"value": ""
								}
							]
						}
					},
					"response": []
				},
				{
					"name": "Admin routes",
					"request": {
						"method": "PATCH",
						"header": [],
						"body": {
							"mode": "raw",
							"raw": "  {\r\n    \"status\": \"shipped\"\r\n  }",
							"options": {
								"raw": {
									"language": "json"
								}
							}
						},
						"url": {
							"raw": "http://localhost:3000/api/orders/admin/orders/1/status",
							"protocol": "http",
							"host": [
								"localhost"
							],
							"port": "3000",
							"path": [
								"api",
								"orders",
								"admin",
								"orders",
								"1",
								"status"
							]
						}
					},
					"response": []
				}
			]
		},
		{
			"name": "manager user",
			"item": [
				{
					"name": "list user",
					"request": {
						"method": "GET",
						"header": [],
						"url": {
							"raw": "http://localhost:3000/api/users/user",
							"protocol": "http",
							"host": [
								"localhost"
							],
							"port": "3000",
							"path": [
								"api",
								"users",
								"user"
							]
						}
					},
					"response": []
				},
				{
					"name": "Lock & unLock",
					"request": {
						"method": "PATCH",
						"header": [],
						"body": {
							"mode": "raw",
							"raw": "",
							"options": {
								"raw": {
									"language": "json"
								}
							}
						},
						"url": {
							"raw": "http://localhost:3000/api/user/3/lock",
							"protocol": "http",
							"host": [
								"localhost"
							],
							"port": "3000",
							"path": [
								"api",
								"user",
								"3",
								"lock"
							]
						}
					},
					"response": []
				}
			]
		}
	]
}